<?xml version="1.0" encoding="utf-8"?>
<resources>
    <style name="Maui.SplashTheme" parent="Theme.MaterialComponents.DayNight.NoActionBar">
        <item name="android:windowBackground">#0d1117</item>
        <item name="android:navigationBarColor">#0d1117</item>
        <item name="android:statusBarColor">#0d1117</item>
    </style>

    <style name="Maui.MainTheme" parent="Theme.MaterialComponents.DayNight.NoActionBar">
        <item name="android:windowBackground">#0d1117</item>
        <item name="android:navigationBarColor">#0d1117</item>
        <item name="android:colorBackground">#0d1117</item>
        <item name="android:statusBarColor">#0d1117</item>
        <item name="textAppearanceBody1">@style/TextAppearance.MaterialComponents.Body1</item>
        <item name="textAppearanceBody2">@style/TextAppearance.MaterialComponents.Body2</item>
        <item name="textAppearanceCaption">@style/TextAppearance.MaterialComponents.Caption</item>
    </style>
</resources>
